{
  "collectionName": "components_shared_call_to_actions",
  "info": {
    "displayName": "Call to Action",
    "description": "Buttons and links for user engagement"
  },
  "options": {},
  "attributes": {
    "text": {
      "type": "string",
      "required": true
    },
    "url": {
      "type": "string",
      "required": true
    },
    "type": {
      "type": "enumeration",
      "enum": ["primary", "secondary", "tertiary", "link"],
      "default": "primary"
    },
    "newTab": {
      "type": "boolean",
      "default": false
    },
    "icon": {
      "type": "string"
    }
  }
} 